{"id":"https-request","name":"HTTPS request","tags":[],"modifiedTime":"2022-10-24T16:14:21.394Z","items":[{"shape":"dummy","area":{"w":760,"h":600},"name":"Root","links":[],"behavior":{"events":[{"id":"3z9EOwBs1","event":"init","actions":[{"id":"xpMwrICPv","element":"tag: reset","method":"hide","args":{"animated":false,"animationDuration":0.5,"transition":"ease-out","inBackground":false}}]}]},"tags":[],"effects":[],"id":"XVJDu0cZj","childItems":[{"shapeProps":{"cornerRadius":0,"fill":{"type":"solid","color":"rgba(159, 227, 249, 0.1)"},"strokeColor":"rgba(50, 175, 209, 1)","strokeSize":1,"strokePattern":"dashed","showName":true},"shape":"dummy","cursor":"default","area":{"x":340,"y":280,"w":40,"h":40,"r":0,"px":0.5,"py":0.5,"sx":1,"sy":1},"opacity":100,"blendMode":"normal","name":"Popup Placeholder","description":"","links":[],"textSlots":{},"behavior":{"events":[]},"selfOpacity":100,"visible":true,"tags":[],"clip":false,"effects":[],"interactionMode":"tooltip","tooltipBackground":"rgba(230,230,230,1.0)","tooltipColor":"rgba(30,30,30,1.0)","id":"Y01H_s81B"},{"id":"5j6mOGKAK","textSlots":{"body":{"text":"<p><strong>HTTPS Request</strong></p>","paddingLeft":0,"paddingRight":0,"paddingTop":0,"paddingBottom":0,"color":"rgba(0,0,0,1.0)","halign":"center","valign":"middle","fontSize":20,"whiteSpace":"normal","font":"Arial"}},"shape":"none","cursor":"default","area":{"x":200,"y":0,"w":320,"h":40,"r":0,"px":0.5,"py":0.5,"sx":1,"sy":1},"opacity":100,"blendMode":"normal","name":"Title","description":"","links":[],"behavior":{"events":[]},"shapeProps":{},"selfOpacity":100,"visible":true,"tags":[],"clip":false,"effects":[],"interactionMode":"tooltip","tooltipBackground":"rgba(230,230,230,1.0)","tooltipColor":"rgba(30,30,30,1.0)"},{"cursor":"default","area":{"x":20,"y":73.80001807892077,"w":688.785934406281,"h":66.19998192107923,"r":0,"px":0.5,"py":0.5,"sx":1,"sy":1},"shape":"none","opacity":100,"blendMode":"normal","name":"HTTPS is basically j","description":"","links":[],"textSlots":{"body":{"text":"<p><strong>Hypertext Transfer Protocol Secure</strong> (HTTPS) is an extension of the <strong>Hypertext Transfer Protocol</strong> (HTTP). It is used for secure communication over a computer network, and is widely used on the Internet. In HTTPS, the communication protocol is encrypted using <strong>Transport Layer Security</strong> (TLS) or, formerly, <strong>Secure Sockets Layer</strong> (SSL). The protocol is therefore also referred to as HTTP over TLS, or HTTP over SSL</p>","halign":"left","valign":"top","paddingLeft":0,"paddingRight":0,"paddingTop":0,"paddingBottom":0,"color":"rgba(0,0,0,1.0)","fontSize":14,"whiteSpace":"normal","font":"Arial"}},"behavior":{"events":[]},"selfOpacity":100,"visible":true,"tags":[],"clip":false,"effects":[],"interactionMode":"tooltip","shapeProps":{},"tooltipBackground":"rgba(230,230,230,1.0)","tooltipColor":"rgba(30,30,30,1.0)","id":"hJBkky878"},{"shapeProps":{"cornerRadius":0,"fill":{"type":"solid","color":"rgba(194, 224, 255, 1)"},"strokeColor":"rgba(133, 129, 129, 1)","strokeSize":2,"strokePattern":"solid"},"shape":"rect","cursor":"pointer","area":{"x":260,"y":160,"w":200,"h":60,"r":0,"px":0.5,"py":0.5,"sx":1,"sy":1},"opacity":100,"blendMode":"normal","name":"Rect 11","description":"","links":[],"textSlots":{"body":{"text":"<p><strong>Application Layer (7)</strong></p><p>HTTP</p>","color":"rgba(0,0,0,1.0)","halign":"center","valign":"middle","fontSize":14,"whiteSpace":"normal","font":"Arial","paddingLeft":0,"paddingRight":0,"paddingTop":0,"paddingBottom":0}},"behavior":{"events":[{"id":"pIamR2ova","event":"clicked","actions":[{"id":"2ALp_RT65","element":"#ZepfYjDTA","method":"moveToItem","args":{"destinationItem":"#Y01H_s81B","matchPoint":"center","animate":false,"duration":2,"movement":"ease-in-out","rotate":false,"rotationOffset":0,"alignWidth":false,"alignHeight":false,"inBackground":false}},{"id":"oB7Kf7rww","element":"#ZepfYjDTA","method":"show","args":{"animated":true,"animationDuration":0.5,"transition":"ease-out","inBackground":false}}]}]},"selfOpacity":100,"visible":true,"tags":["buttons"],"clip":false,"effects":[],"interactionMode":"tooltip","tooltipBackground":"rgba(230,230,230,1.0)","tooltipColor":"rgba(30,30,30,1.0)","id":"61C5i_Lti"},{"id":"KxJ-m_LqEk","shapeProps":{"cornerRadius":0,"fill":{"type":"solid","color":"rgba(255, 227, 167, 1)"},"strokeColor":"rgba(133, 129, 129, 1)","strokeSize":2,"strokePattern":"solid"},"shape":"rect","cursor":"pointer","area":{"x":260,"y":220,"w":200,"h":60,"r":0,"px":0.5,"py":0.5,"sx":1,"sy":1},"opacity":100,"blendMode":"normal","name":"TLS","description":"<p>TLS&nbsp;is a cryptographic protocol that provides end-to-end security of data sent between applications over the Internet. It is mostly familiar to users through its use in secure web browsing, and in particular the padlock icon that appears in web browsers when a secure session (TLS Handshake) is established.</p><p></p><p>TLS uses asymmetric cryptography for securely generating and exchanging a session key. The session key is then used for encrypting the data transmitted by one party, and for decrypting the data received at the other end. Once the session is over, the session key is discarded.</p><p></p><p>variety of different key generation and exchange methods can be used, including RSA, Diffie-Hellman (DH), Ephemeral Diffie-Hellman (DHE), Elliptic Curve Diffie-Hellman (ECDH) and Ephemeral Elliptic Curve Diffie-Hellman (ECDHE)</p>","links":[],"textSlots":{"body":{"text":"<p><strong>Presentation Layer (6)</strong></p><p>TLS</p>","color":"rgba(0,0,0,1.0)","halign":"center","valign":"middle","fontSize":14,"whiteSpace":"normal","font":"Arial","paddingLeft":0,"paddingRight":0,"paddingTop":0,"paddingBottom":0}},"behavior":{"events":[]},"selfOpacity":100,"visible":true,"tags":["buttons"],"clip":false,"effects":[],"interactionMode":"tooltip","tooltipBackground":"rgba(230,230,230,1.0)","tooltipColor":"rgba(30,30,30,1.0)"},{"cursor":"default","area":{"x":15.20917782026764,"y":161.1197705544933,"w":181.52961803895792,"h":49.52964418021032,"r":0,"px":0.5,"py":0.5,"sx":1,"sy":1},"shape":"none","opacity":100,"blendMode":"normal","name":"On the OSI model HTT","description":"","links":[],"textSlots":{"body":{"text":"<p><em>On the OSI model HTTP operates in the Application Layer</em></p>","halign":"left","valign":"top","paddingLeft":0,"paddingRight":0,"paddingTop":0,"paddingBottom":0,"color":"rgba(55, 134, 184, 1)","fontSize":14,"whiteSpace":"normal","font":"Arial"}},"behavior":{"events":[]},"selfOpacity":100,"visible":true,"tags":[],"clip":false,"effects":[],"interactionMode":"tooltip","shapeProps":{},"tooltipBackground":"rgba(230,230,230,1.0)","tooltipColor":"rgba(30,30,30,1.0)","id":"WYDoOWqlI"},{"id":"jr5RqX5sP","shapeProps":{"cornerRadius":0,"fill":{"type":"solid","color":"rgba(217, 255, 252, 1)"},"strokeColor":"rgba(30,30,30,1.0)","strokeSize":2,"strokePattern":"solid"},"shape":"rect","cursor":"default","area":{"x":260,"y":280,"w":200,"h":60,"r":0,"px":0.5,"py":0.5,"sx":1,"sy":1},"opacity":30,"blendMode":"normal","name":"Rect 14","description":"","links":[],"textSlots":{"body":{"text":"<p><strong>Session Layer (5)</strong></p>","color":"rgba(0,0,0,1.0)","halign":"center","valign":"middle","fontSize":14,"whiteSpace":"normal","font":"Arial","paddingLeft":0,"paddingRight":0,"paddingTop":0,"paddingBottom":0}},"behavior":{"events":[]},"selfOpacity":100,"visible":true,"tags":[],"clip":false,"effects":[],"interactionMode":"tooltip","tooltipBackground":"rgba(230,230,230,1.0)","tooltipColor":"rgba(30,30,30,1.0)"},{"id":"oD72D7uXL","shapeProps":{"cornerRadius":0,"fill":{"type":"solid","color":"rgba(217, 255, 252, 1)"},"strokeColor":"rgba(30,30,30,1.0)","strokeSize":2,"strokePattern":"solid"},"shape":"rect","cursor":"default","area":{"x":260,"y":340,"w":200,"h":60,"r":0,"px":0.5,"py":0.5,"sx":1,"sy":1},"opacity":30,"blendMode":"normal","name":"Rect 15","description":"","links":[],"textSlots":{"body":{"text":"<p><strong>Transport Layer (4)</strong></p><p>TCP</p>","color":"rgba(0,0,0,1.0)","halign":"center","valign":"middle","fontSize":14,"whiteSpace":"normal","font":"Arial","paddingLeft":0,"paddingRight":0,"paddingTop":0,"paddingBottom":0}},"behavior":{"events":[]},"selfOpacity":100,"visible":true,"tags":[],"clip":false,"effects":[],"interactionMode":"tooltip","tooltipBackground":"rgba(230,230,230,1.0)","tooltipColor":"rgba(30,30,30,1.0)"},{"id":"xObRWvSrc","shapeProps":{"cornerRadius":0,"fill":{"type":"solid","color":"rgba(217, 255, 252, 1)"},"strokeColor":"rgba(30,30,30,1.0)","strokeSize":2,"strokePattern":"solid"},"shape":"rect","cursor":"default","area":{"x":260,"y":400,"w":200,"h":60,"r":0,"px":0.5,"py":0.5,"sx":1,"sy":1},"opacity":30,"blendMode":"normal","name":"Rect 16","description":"","links":[],"textSlots":{"body":{"text":"<p><strong>Network Layer (3)</strong></p><p>IP</p>","color":"rgba(0,0,0,1.0)","halign":"center","valign":"middle","fontSize":14,"whiteSpace":"normal","font":"Arial","paddingLeft":0,"paddingRight":0,"paddingTop":0,"paddingBottom":0}},"behavior":{"events":[]},"selfOpacity":100,"visible":true,"tags":[],"clip":false,"effects":[],"interactionMode":"tooltip","tooltipBackground":"rgba(230,230,230,1.0)","tooltipColor":"rgba(30,30,30,1.0)"},{"id":"WcWK0PYa3","shapeProps":{"cornerRadius":0,"fill":{"type":"solid","color":"rgba(217, 255, 252, 1)"},"strokeColor":"rgba(30,30,30,1.0)","strokeSize":2,"strokePattern":"solid"},"shape":"rect","cursor":"default","area":{"x":260,"y":460,"w":200,"h":60,"r":0,"px":0.5,"py":0.5,"sx":1,"sy":1},"opacity":30,"blendMode":"normal","name":"Rect 17","description":"","links":[],"textSlots":{"body":{"text":"<p><strong>Data link layer (2)</strong></p><p>Ethernet</p>","color":"rgba(0,0,0,1.0)","halign":"center","valign":"middle","fontSize":14,"whiteSpace":"normal","font":"Arial","paddingLeft":0,"paddingRight":0,"paddingTop":0,"paddingBottom":0}},"behavior":{"events":[]},"selfOpacity":100,"visible":true,"tags":[],"clip":false,"effects":[],"interactionMode":"tooltip","tooltipBackground":"rgba(230,230,230,1.0)","tooltipColor":"rgba(30,30,30,1.0)"},{"id":"FcICZfhRQ5","shapeProps":{"cornerRadius":0,"fill":{"type":"solid","color":"rgba(217, 255, 252, 1)"},"strokeColor":"rgba(30,30,30,1.0)","strokeSize":2,"strokePattern":"solid"},"shape":"rect","cursor":"default","area":{"x":260,"y":520,"w":200,"h":60,"r":0,"px":0.5,"py":0.5,"sx":1,"sy":1},"opacity":30,"blendMode":"normal","name":"Rect 18","description":"","links":[],"textSlots":{"body":{"text":"<p><strong>Physical layer (1)</strong></p><p></p>","color":"rgba(0,0,0,1.0)","halign":"center","valign":"middle","fontSize":14,"whiteSpace":"normal","font":"Arial","paddingLeft":0,"paddingRight":0,"paddingTop":0,"paddingBottom":0}},"behavior":{"events":[]},"selfOpacity":100,"visible":true,"tags":[],"clip":false,"effects":[],"interactionMode":"tooltip","tooltipBackground":"rgba(230,230,230,1.0)","tooltipColor":"rgba(30,30,30,1.0)"},{"id":"VJIqHxxO-","cursor":"default","area":{"x":513.0393768937172,"y":277.1082982791587,"w":210.36406884858988,"h":66.03594961366964,"r":0,"px":0.5,"py":0.5,"sx":1,"sy":1},"shape":"none","opacity":100,"blendMode":"normal","name":"On the OSI model HTT 2","description":"","links":[],"textSlots":{"body":{"text":"<p><em>TLS operates in Presentation Layer which means that it just encrypts HTTP requests and responses</em></p>","halign":"left","valign":"top","paddingLeft":0,"paddingRight":0,"paddingTop":0,"paddingBottom":0,"color":"rgba(173, 120, 12, 1)","fontSize":14,"whiteSpace":"normal","font":"Arial"}},"behavior":{"events":[]},"selfOpacity":100,"visible":true,"tags":[],"clip":false,"effects":[],"interactionMode":"tooltip","shapeProps":{},"tooltipBackground":"rgba(230,230,230,1.0)","tooltipColor":"rgba(30,30,30,1.0)"},{"id":"yP_lbVknb","area":{"x":463.73027991126384,"y":247.73822317193782,"w":84.35448688489139,"h":18.266280879080895,"r":-165,"px":0.5,"py":0.5,"sx":1,"sy":1},"name":"Drawing 3","shape":"path","shapeProps":{"paths":[{"pos":"relative","closed":false,"points":[{"t":"L","x":0,"y":34.9206183913144},{"t":"B","x":37.62139402797618,"y":99.38696966885738,"x1":-26.62917781765889,"y1":-7.3538433004666155,"x2":26.62917781765889,"y2":7.35384330046646},{"t":"L","x":94.51188517370554,"y":25.87877437854271}]},{"pos":"relative","closed":false,"points":[{"t":"L","x":73.31163150472388,"y":2.5914477593879726},{"t":"B","x":99.97820953467169,"y":4.467246262625347,"x1":-0.6816472024596393,"y1":-7.869691753433261,"x2":0.6816472024595045,"y2":7.869691753433572},{"t":"L","x":80.01828290596232,"y":92.5470816727375}]}],"strokeSize":3,"closed":false,"fill":{"type":"none"},"strokeColor":"rgba(219, 161, 58, 1)","strokePattern":"solid","sourceCap":"empty","sourceCapSize":20,"sourceCapFill":"rgba(30,30,30,1.0)","destinationCap":"empty","destinationCapSize":20,"destinationCapFill":"rgba(30,30,30,1.0)"},"textSlots":{},"opacity":100,"selfOpacity":100,"visible":true,"tags":[],"blendMode":"normal","cursor":"default","clip":false,"effects":[],"description":"","interactionMode":"side-panel","behavior":{"events":[]},"tooltipBackground":"rgba(230,230,230,1.0)","tooltipColor":"rgba(30,30,30,1.0)"},{"area":{"x":129.30958539196942,"y":196.46736545087336,"w":123.94992999238768,"h":19.36153376629232,"r":0,"px":0.5,"py":0.5,"sx":1,"sy":1},"name":"Drawing","shape":"path","shapeProps":{"paths":[{"pos":"relative","closed":false,"points":[{"t":"L","x":0,"y":51.817354297587045},{"t":"B","x":43.757260446681585,"y":99.45868214663102,"x1":-18.122564741368546,"y1":-6.937847429263397,"x2":18.12256474136852,"y2":6.937847429263397},{"t":"L","x":96.26504742547364,"y":24.414850977756423}]},{"pos":"relative","closed":false,"points":[{"t":"L","x":81.83715287009704,"y":2.4448534515824436},{"t":"B","x":99.985170435176,"y":4.214540850643168,"x1":-0.4638969945649037,"y1":-7.424515109968363,"x2":0.4638969945649037,"y2":7.424515109968363},{"t":"L","x":86.40138406976007,"y":87.31183225352453}]}],"strokeSize":3,"closed":false,"fill":{"type":"none"},"strokeColor":"rgba(73, 163, 219, 1)","strokePattern":"solid","sourceCap":"empty","sourceCapSize":20,"sourceCapFill":"rgba(30,30,30,1.0)","destinationCap":"empty","destinationCapSize":20,"destinationCapFill":"rgba(30,30,30,1.0)"},"textSlots":{},"opacity":100,"selfOpacity":100,"visible":true,"tags":[],"blendMode":"normal","cursor":"default","clip":false,"effects":[],"description":"","interactionMode":"side-panel","behavior":{"events":[]},"tooltipBackground":"rgba(230,230,230,1.0)","tooltipColor":"rgba(30,30,30,1.0)","id":"X7lImpFU7"},{"shapeProps":{"cornerRadius":0,"fill":{"type":"solid","color":"rgba(159, 227, 249, 0.1)"},"strokeColor":"rgba(50, 175, 209, 1)","strokeSize":1,"strokePattern":"dashed","showName":true},"shape":"dummy","cursor":"default","area":{"x":1000,"y":0,"w":1900,"h":500,"r":0,"px":0.5,"py":0.5,"sx":1,"sy":1},"opacity":100,"blendMode":"normal","name":"container","description":"","links":[],"textSlots":{},"behavior":{"events":[]},"selfOpacity":100,"visible":true,"tags":[],"clip":false,"effects":[],"interactionMode":"tooltip","tooltipBackground":"rgba(230,230,230,1.0)","tooltipColor":"rgba(30,30,30,1.0)","id":"8BAeLQh_e","locked":true,"childItems":[{"shapeProps":{"cornerRadius":15,"fill":{"type":"solid","color":"rgba(240,240,240,1.0)"},"strokeColor":"rgba(182, 181, 181, 1)","strokeSize":1,"strokePattern":"solid"},"shape":"rect","cursor":"default","area":{"x":40,"y":20,"w":760,"h":420,"r":0,"px":0.5,"py":0.5,"sx":1,"sy":1},"opacity":100,"blendMode":"normal","name":"HTTP Request","description":"","links":[],"textSlots":{"body":{"text":"","color":"rgba(0,0,0,1.0)","halign":"center","valign":"middle","fontSize":14,"whiteSpace":"normal","font":"Arial","paddingLeft":0,"paddingRight":0,"paddingTop":0,"paddingBottom":0}},"behavior":{"events":[]},"selfOpacity":100,"visible":true,"tags":["reset"],"clip":false,"effects":[{"id":"EdOSUGWf2","effect":"drop-shadow","name":"Drop Shadow","args":{"color":"rgba(0,0,0,1.0)","dx":5,"dy":5,"blur":14,"opacity":50,"inside":false}}],"interactionMode":"tooltip","tooltipBackground":"rgba(230,230,230,1.0)","tooltipColor":"rgba(30,30,30,1.0)","id":"ZepfYjDTA","childItems":[{"shapeProps":{"cornerRadius":8.3,"fill":{"type":"solid","color":"rgba(255, 255, 255, 1)"},"strokeColor":"rgba(211, 211, 211, 1)","strokeSize":1,"strokePattern":"solid"},"shape":"rect","cursor":"default","area":{"x":20,"y":80,"w":720,"h":260,"r":0,"px":0.5,"py":0.5,"sx":1,"sy":1},"opacity":100,"blendMode":"normal","name":"Rect 13","description":"","links":[],"textSlots":{"body":{"text":"","color":"rgba(0,0,0,1.0)","halign":"center","valign":"middle","fontSize":14,"whiteSpace":"normal","font":"Arial","paddingLeft":0,"paddingRight":0,"paddingTop":0,"paddingBottom":0}},"behavior":{"events":[]},"selfOpacity":100,"visible":true,"tags":[],"clip":false,"effects":[],"interactionMode":"tooltip","tooltipBackground":"rgba(230,230,230,1.0)","tooltipColor":"rgba(30,30,30,1.0)","id":"aQzxCesJz","childItems":[{"shapeProps":{"cornerRadius":0,"fill":{"type":"none","color":"rgba(240,240,240,1.0)"},"strokeColor":"rgba(224, 224, 224, 1)","strokeSize":2,"strokePattern":"dotted"},"shape":"rect","cursor":"default","area":{"x":20,"y":40,"w":620,"h":120,"r":0,"px":0.5,"py":0.5,"sx":1,"sy":1},"opacity":100,"blendMode":"normal","name":"Rect 21","description":"","links":[],"textSlots":{"body":{"text":"","color":"rgba(0,0,0,1.0)","halign":"center","valign":"middle","fontSize":14,"whiteSpace":"normal","font":"Arial","paddingLeft":0,"paddingRight":0,"paddingTop":0,"paddingBottom":0}},"behavior":{"events":[]},"selfOpacity":100,"visible":true,"tags":[],"clip":false,"effects":[],"interactionMode":"tooltip","tooltipBackground":"rgba(230,230,230,1.0)","tooltipColor":"rgba(30,30,30,1.0)","id":"8cjJgNeqk"},{"id":"p-P3mHjgp","shapeProps":{"cornerRadius":0,"fill":{"type":"solid","color":"rgba(240, 240, 240, 0)"},"strokeColor":"rgba(30,30,30,1.0)","strokeSize":0,"strokePattern":"solid"},"shape":"rect","cursor":"pointer","area":{"x":20,"y":80,"w":540,"h":20,"r":0,"px":0.5,"py":0.5,"sx":1,"sy":1},"opacity":100,"blendMode":"normal","name":"Accept","description":"<p>The <strong>Accept</strong> request HTTP header indicates which content types, expressed as <a href=\"https://developer.mozilla.org/en-US/docs/Web/HTTP/Basics_of_HTTP/MIME_types\" rel=\"noopener noreferrer nofollow\"><u>MIME types</u></a>, the client is able to understand. The server uses <a href=\"https://developer.mozilla.org/en-US/docs/Web/HTTP/Content_negotiation\" rel=\"noopener noreferrer nofollow\"><u>content negotiation</u></a> to select one of the proposals and informs the client of the choice with the <strong>Content-Type</strong> response header. Browsers set required values for this header based on the context of the request. For example, a browser uses different values in a request when fetching a CSS stylesheet, image, video, or a script.</p>","links":[],"textSlots":{"body":{"text":"<p>Accept: text/html,application/xml;q=0.9,image/avif,image/webp,image/apng,*/*;q=0.8</p>","color":"rgba(0,0,0,1.0)","halign":"left","valign":"middle","fontSize":14,"whiteSpace":"normal","font":"Arial","paddingLeft":2,"paddingRight":2,"paddingTop":2,"paddingBottom":0}},"behavior":{"events":[]},"selfOpacity":100,"visible":true,"tags":["format-part"],"clip":false,"effects":[],"interactionMode":"tooltip","tooltipBackground":"rgba(230,230,230,1.0)","tooltipColor":"rgba(30,30,30,1.0)"},{"shapeProps":{"cornerRadius":0,"fill":{"type":"solid","color":"rgba(240, 240, 240, 0)"},"strokeColor":"rgba(30,30,30,1.0)","strokeSize":0,"strokePattern":"solid"},"shape":"rect","cursor":"pointer","area":{"x":20,"y":20,"w":40,"h":20,"r":0,"px":0.5,"py":0.5,"sx":1,"sy":1},"opacity":100,"blendMode":"normal","name":"HTTP Method","description":"<p>HTTP defines a set of <strong>request methods</strong> to indicate the desired action to be performed for a given resource. Although they can also be nouns, these request methods are sometimes referred to as <em>HTTP verbs</em>.</p><p></p><p>Method defined in HTTP/1.1 are: GET, HEAD, POST, PUT, PATCH, OPTION, TRACE, DELETE, CONNECT</p>","links":[],"textSlots":{"body":{"text":"<p>GET</p>","color":"rgba(0,0,0,1.0)","halign":"left","valign":"middle","fontSize":14,"whiteSpace":"normal","font":"Arial","paddingLeft":2,"paddingRight":2,"paddingTop":2,"paddingBottom":0}},"behavior":{"events":[]},"selfOpacity":100,"visible":true,"tags":["format-part"],"clip":false,"effects":[],"interactionMode":"tooltip","tooltipBackground":"rgba(230,230,230,1.0)","tooltipColor":"rgba(30,30,30,1.0)","id":"EB5wTC9et"},{"id":"tGrtcC25-","shapeProps":{"cornerRadius":0,"fill":{"type":"solid","color":"rgba(240, 240, 240, 0)"},"strokeColor":"rgba(30,30,30,1.0)","strokeSize":0,"strokePattern":"solid"},"shape":"rect","cursor":"pointer","area":{"x":60,"y":20,"w":15,"h":20,"r":0,"px":0.5,"py":0.5,"sx":1,"sy":1},"opacity":100,"blendMode":"normal","name":"Request path","description":"<p>Path to a resource on a server</p>","links":[],"textSlots":{"body":{"text":"<p>/</p>","color":"rgba(0,0,0,1.0)","halign":"left","valign":"middle","fontSize":14,"whiteSpace":"normal","font":"Arial","paddingLeft":2,"paddingRight":2,"paddingTop":2,"paddingBottom":0}},"behavior":{"events":[]},"selfOpacity":100,"visible":true,"tags":["format-part"],"clip":false,"effects":[],"interactionMode":"tooltip","tooltipBackground":"rgba(230,230,230,1.0)","tooltipColor":"rgba(30,30,30,1.0)"},{"id":"-gNrHz6eqh","shapeProps":{"cornerRadius":0,"fill":{"type":"solid","color":"rgba(240, 240, 240, 0)"},"strokeColor":"rgba(30,30,30,1.0)","strokeSize":0,"strokePattern":"solid"},"shape":"rect","cursor":"pointer","area":{"x":75,"y":20,"w":65,"h":20,"r":0,"px":0.5,"py":0.5,"sx":1,"sy":1},"opacity":100,"blendMode":"normal","name":"HTTP protocol version","description":"<p>HTTP protocol version</p>","links":[],"textSlots":{"body":{"text":"<p>HTTP/1.1</p>","color":"rgba(0,0,0,1.0)","halign":"left","valign":"middle","fontSize":14,"whiteSpace":"normal","font":"Arial","paddingLeft":2,"paddingRight":2,"paddingTop":2,"paddingBottom":0}},"behavior":{"events":[]},"selfOpacity":100,"visible":true,"tags":["format-part"],"clip":false,"effects":[],"interactionMode":"tooltip","tooltipBackground":"rgba(230,230,230,1.0)","tooltipColor":"rgba(30,30,30,1.0)"},{"id":"AQON3mPbL","shapeProps":{"cornerRadius":0,"fill":{"type":"solid","color":"rgba(240, 240, 240, 0)"},"strokeColor":"rgba(30,30,30,1.0)","strokeSize":0,"strokePattern":"solid"},"shape":"rect","cursor":"pointer","area":{"x":20,"y":40,"w":125,"h":20,"r":0,"px":0.5,"py":0.5,"sx":1,"sy":1},"opacity":100,"blendMode":"normal","name":"Hostname or domain name","description":"<p>The <strong>Host</strong> request header specifies the host and port number of the server to which the request is being sent.</p><p>If no port is included, the default port for the service requested is implied (e.g., 443 for an HTTPS URL, and 80 for an HTTP URL).</p><p>A <strong>Host</strong> header field must be sent in all HTTP/1.1 request messages.</p>","links":[],"textSlots":{"body":{"text":"<p>Host: schemio.app</p>","color":"rgba(0,0,0,1.0)","halign":"left","valign":"middle","fontSize":14,"whiteSpace":"normal","font":"Arial","paddingLeft":2,"paddingRight":2,"paddingTop":2,"paddingBottom":0}},"behavior":{"events":[]},"selfOpacity":100,"visible":true,"tags":["format-part"],"clip":false,"effects":[],"interactionMode":"tooltip","tooltipBackground":"rgba(230,230,230,1.0)","tooltipColor":"rgba(30,30,30,1.0)"},{"id":"g18kRoOkJ","shapeProps":{"cornerRadius":0,"fill":{"type":"solid","color":"rgba(240, 240, 240, 0)"},"strokeColor":"rgba(30,30,30,1.0)","strokeSize":0,"strokePattern":"solid"},"shape":"rect","cursor":"pointer","area":{"x":20,"y":60,"w":340,"h":20,"r":0,"px":0.5,"py":0.5,"sx":1,"sy":1},"opacity":100,"blendMode":"normal","name":"User-Agent","description":"<p>The <strong>User-Agent</strong> header is a characteristic string that lets servers and network peers identify the application, operating system, vendor, and/or version of the requesting user agent</p>","links":[],"textSlots":{"body":{"text":"<p>User-Agent: Mozilla/5.0 (X11; Linux x86_64; rv:10.0) Gecko/20100101 Firefox/10.0</p>","color":"rgba(0,0,0,1.0)","halign":"left","valign":"middle","fontSize":14,"whiteSpace":"normal","font":"Arial","paddingLeft":2,"paddingRight":2,"paddingTop":2,"paddingBottom":0}},"behavior":{"events":[]},"selfOpacity":100,"visible":true,"tags":["format-part"],"clip":false,"effects":[],"interactionMode":"tooltip","tooltipBackground":"rgba(230,230,230,1.0)","tooltipColor":"rgba(30,30,30,1.0)"},{"id":"TTIAljtkO","shapeProps":{"cornerRadius":0,"fill":{"type":"solid","color":"rgba(240, 240, 240, 0)"},"strokeColor":"rgba(30,30,30,1.0)","strokeSize":0,"strokePattern":"solid"},"shape":"rect","cursor":"pointer","area":{"x":20,"y":100,"w":215,"h":20,"r":0,"px":0.5,"py":0.5,"sx":1,"sy":1},"opacity":100,"blendMode":"normal","name":"Accept-Encoding","description":"<p>The <strong>Accept-Encoding</strong> request HTTP header indicates the content encoding (usually a compression algorithm) that the client can understand. The server uses <a href=\"https://developer.mozilla.org/en-US/docs/Web/HTTP/Content_negotiation\" rel=\"noopener noreferrer nofollow\"><u>content negotiation</u></a> to select one of the proposals and informs the client of that choice with the <strong>Content-Encoding</strong> response header.</p>","links":[],"textSlots":{"body":{"text":"<p>Accept-Encoding: gzip, deflate, br</p>","color":"rgba(0,0,0,1.0)","halign":"left","valign":"middle","fontSize":14,"whiteSpace":"normal","font":"Arial","paddingLeft":2,"paddingRight":2,"paddingTop":2,"paddingBottom":0}},"behavior":{"events":[]},"selfOpacity":100,"visible":true,"tags":["format-part"],"clip":false,"effects":[],"interactionMode":"tooltip","tooltipBackground":"rgba(230,230,230,1.0)","tooltipColor":"rgba(30,30,30,1.0)"},{"id":"sfaMzjwK7","shapeProps":{"cornerRadius":0,"fill":{"type":"solid","color":"rgba(240, 240, 240, 0)"},"strokeColor":"rgba(30,30,30,1.0)","strokeSize":0,"strokePattern":"solid"},"shape":"rect","cursor":"pointer","area":{"x":20,"y":140,"w":150,"h":20,"r":0,"px":0.5,"py":0.5,"sx":1,"sy":1},"opacity":100,"blendMode":"normal","name":"Connection","description":"<p>The <strong>Connection</strong> general header controls whether the network connection stays open after the current transaction finishes. If the value sent is <strong>keep-alive</strong>, the connection is persistent and not closed, allowing for subsequent requests to the same server to be done.</p>","links":[],"textSlots":{"body":{"text":"<p>Connection: keep-alive</p>","color":"rgba(0,0,0,1.0)","halign":"left","valign":"middle","fontSize":14,"whiteSpace":"normal","font":"Arial","paddingLeft":2,"paddingRight":2,"paddingTop":2,"paddingBottom":0}},"behavior":{"events":[]},"selfOpacity":100,"visible":true,"tags":["format-part"],"clip":false,"effects":[],"interactionMode":"tooltip","tooltipBackground":"rgba(230,230,230,1.0)","tooltipColor":"rgba(30,30,30,1.0)"},{"id":"6R4ERTH1nN","shapeProps":{"cornerRadius":0,"fill":{"type":"solid","color":"rgba(240, 240, 240, 0)"},"strokeColor":"rgba(30,30,30,1.0)","strokeSize":0,"strokePattern":"solid"},"shape":"rect","cursor":"pointer","area":{"x":20,"y":120,"w":225,"h":20,"r":0,"px":0.5,"py":0.5,"sx":1,"sy":1},"opacity":100,"blendMode":"normal","name":"Accept-Language","description":"<p>The <strong>Accept-Language</strong> request HTTP header indicates the natural language and locale that the client prefers. The server uses <a href=\"https://developer.mozilla.org/en-US/docs/Web/HTTP/Content_negotiation\" rel=\"noopener noreferrer nofollow\"><u>content negotiation</u></a> to select one of the proposals and informs the client of the choice with the <strong>Content-Language</strong> response header. Browsers set required values for this header according to their active user interface language. Users rarely change it, and such changes are not recommended because they may lead to fingerprinting.</p>","links":[],"textSlots":{"body":{"text":"<p>Accept-Language: en-GB,en;q=0.5</p>","color":"rgba(0,0,0,1.0)","halign":"left","valign":"middle","fontSize":14,"whiteSpace":"normal","font":"Arial","paddingLeft":2,"paddingRight":2,"paddingTop":2,"paddingBottom":0}},"behavior":{"events":[]},"selfOpacity":100,"visible":true,"tags":["format-part"],"clip":false,"effects":[],"interactionMode":"tooltip","tooltipBackground":"rgba(230,230,230,1.0)","tooltipColor":"rgba(30,30,30,1.0)"},{"id":"7Bhnm69p2","shapeProps":{"cornerRadius":0,"fill":{"type":"solid","color":"rgba(240, 240, 240, 0)"},"strokeColor":"rgba(30,30,30,1.0)","strokeSize":0,"strokePattern":"solid"},"shape":"rect","cursor":"pointer","area":{"x":20,"y":160,"w":680,"h":20,"r":0,"px":0.5,"py":0.5,"sx":1,"sy":1},"opacity":100,"blendMode":"normal","name":"empty line","description":"<p>A blank line indicating all meta-information for the request has been sent. Anything that goes after this line will be treated as a request payload</p>","links":[],"textSlots":{"body":{"text":"<p><em> empty line</em></p>","color":"rgba(43, 168, 173, 1)","halign":"left","valign":"middle","fontSize":14,"whiteSpace":"normal","font":"Arial","paddingLeft":2,"paddingRight":2,"paddingTop":2,"paddingBottom":0}},"behavior":{"events":[]},"selfOpacity":100,"visible":true,"tags":["format-part"],"clip":false,"effects":[],"interactionMode":"tooltip","tooltipBackground":"rgba(230,230,230,1.0)","tooltipColor":"rgba(30,30,30,1.0)"},{"id":"bOY7DOpXA","shapeProps":{"cornerRadius":0,"fill":{"type":"solid","color":"rgba(240, 240, 240, 0)"},"strokeColor":"rgba(30,30,30,1.0)","strokeSize":0,"strokePattern":"solid"},"shape":"rect","cursor":"pointer","area":{"x":20,"y":180,"w":680,"h":60,"r":0,"px":0.5,"py":0.5,"sx":1,"sy":1},"opacity":100,"blendMode":"normal","name":"Request Body","description":"<p>An optional <em>body</em> containing data associated with the request (like content of an HTML form), or the document associated with a response. The presence of the body and its size is specified by the start-line and HTTP headers.</p>","links":[],"textSlots":{"body":{"text":"<p><em>Data (e.g. for POST, PUT, PATCH requests)</em></p>","color":"rgba(43, 168, 173, 1)","halign":"left","valign":"middle","fontSize":14,"whiteSpace":"normal","font":"Arial","paddingLeft":2,"paddingRight":2,"paddingTop":2,"paddingBottom":0}},"behavior":{"events":[]},"selfOpacity":100,"visible":true,"tags":["format-part"],"clip":false,"effects":[],"interactionMode":"tooltip","tooltipBackground":"rgba(230,230,230,1.0)","tooltipColor":"rgba(30,30,30,1.0)"},{"shapeProps":{"fill":{"type":"none","color":"rgba(240,240,240,1.0)"},"style":"curly","strokeColor":"rgba(160, 160, 160, 1)","strokeSize":2,"strokePattern":"solid"},"shape":"bracket","cursor":"default","area":{"x":655,"y":40,"w":20,"h":120,"r":0,"px":0.5,"py":0.5,"sx":1,"sy":1},"opacity":100,"blendMode":"normal","name":"Curly Bracket","description":"","links":[],"textSlots":{},"behavior":{"events":[]},"selfOpacity":100,"visible":true,"tags":[],"clip":false,"effects":[],"interactionMode":"tooltip","tooltipBackground":"rgba(230,230,230,1.0)","tooltipColor":"rgba(30,30,30,1.0)","id":"Na9Kpv0Fy"},{"cursor":"default","area":{"x":642.6271245765881,"y":92.55470868142882,"w":94.9275841048408,"h":19.818166741983156,"r":-90,"px":0.5,"py":0.5,"sx":1,"sy":1},"shape":"none","opacity":100,"blendMode":"normal","name":"HTTP Headers","description":"","links":[],"textSlots":{"body":{"text":"<p>HTTP Headers</p>","halign":"left","valign":"top","paddingLeft":0,"paddingRight":0,"paddingTop":0,"paddingBottom":0,"color":"rgba(0,0,0,1.0)","fontSize":14,"whiteSpace":"normal","font":"Arial"}},"behavior":{"events":[]},"selfOpacity":100,"visible":true,"tags":[],"clip":false,"effects":[],"interactionMode":"tooltip","shapeProps":{},"tooltipBackground":"rgba(230,230,230,1.0)","tooltipColor":"rgba(30,30,30,1.0)","id":"VQS76l_lJ"}]},{"cursor":"default","area":{"x":260,"y":17,"w":200,"h":23,"r":0,"px":0.5,"py":0.5,"sx":1,"sy":1},"shape":"none","opacity":100,"blendMode":"normal","name":"HTTP Request Format","description":"","links":[],"textSlots":{"body":{"text":"<p><strong>HTTP Request Format</strong></p>","halign":"left","valign":"top","paddingLeft":0,"paddingRight":0,"paddingTop":0,"paddingBottom":0,"color":"rgba(0,0,0,1.0)","fontSize":18,"whiteSpace":"normal","font":"Arial"}},"behavior":{"events":[]},"selfOpacity":100,"visible":true,"tags":[],"clip":false,"effects":[],"interactionMode":"tooltip","shapeProps":{},"tooltipBackground":"rgba(230,230,230,1.0)","tooltipColor":"rgba(30,30,30,1.0)","id":"_UoNiyYmy"},{"shapeProps":{"cornerRadius":9.1,"fill":{"type":"solid","color":"rgba(67, 179, 217, 1)"},"strokeColor":"rgba(30,30,30,1.0)","strokeSize":0,"strokePattern":"solid"},"shape":"rect","cursor":"pointer","area":{"x":130,"y":360,"w":240,"h":40,"r":0,"px":0.5,"py":0.5,"sx":1,"sy":1},"opacity":100,"blendMode":"normal","name":"Rounded Rect","description":"","links":[],"textSlots":{"body":{"text":"<p>See HTTP Response Format</p>","color":"rgba(255, 255, 255, 1)","halign":"center","valign":"middle","fontSize":14,"whiteSpace":"normal","font":"Arial","paddingLeft":0,"paddingRight":0,"paddingTop":0,"paddingBottom":0}},"behavior":{"events":[{"id":"LgfZb2zoj","event":"clicked","actions":[{"id":"hbtXjwA3o","element":"#7dU2eXDPs","method":"moveToItem","args":{"destinationItem":"#ZepfYjDTA","matchPoint":"center","animate":false,"duration":2,"movement":"ease-in-out","rotate":false,"rotationOffset":0,"alignWidth":false,"alignHeight":false,"inBackground":false}},{"id":"p-p-7E84i","element":"#7dU2eXDPs","method":"show","args":{"animated":true,"animationDuration":0.5,"transition":"ease-out","inBackground":false}},{"id":"CEauIrmqY","element":"#ZepfYjDTA","method":"hide","args":{"animated":false,"animationDuration":0.5,"transition":"ease-out","inBackground":true}}]}]},"selfOpacity":100,"visible":true,"tags":["buttons"],"clip":false,"effects":[],"interactionMode":"tooltip","tooltipBackground":"rgba(230,230,230,1.0)","tooltipColor":"rgba(30,30,30,1.0)","id":"_OZVzeo4B"},{"id":"fV-VlPEz_","shapeProps":{"cornerRadius":9.1,"fill":{"type":"solid","color":"rgba(210, 208, 208, 1)"},"strokeColor":"rgba(0, 0, 0, 1)","strokeSize":0,"strokePattern":"solid"},"shape":"rect","cursor":"pointer","area":{"x":390,"y":360,"w":240,"h":40,"r":0,"px":0.5,"py":0.5,"sx":1,"sy":1},"opacity":100,"blendMode":"normal","name":"Rounded Rect 2","description":"","links":[],"textSlots":{"body":{"text":"<p>Close</p>","color":"rgba(0,0,0,1.0)","halign":"center","valign":"middle","fontSize":14,"whiteSpace":"normal","font":"Arial","paddingLeft":0,"paddingRight":0,"paddingTop":0,"paddingBottom":0}},"behavior":{"events":[{"id":"Yiewrv6za","event":"clicked","actions":[{"id":"XBpbsyKU4","element":"#ZepfYjDTA","method":"hide","args":{"animated":true,"animationDuration":0.5,"transition":"ease-out","inBackground":false}}]}]},"selfOpacity":100,"visible":true,"tags":["buttons"],"clip":false,"effects":[],"interactionMode":"tooltip","tooltipBackground":"rgba(230,230,230,1.0)","tooltipColor":"rgba(30,30,30,1.0)"},{"cursor":"default","area":{"x":40,"y":50,"w":660,"h":20.19997805393041,"r":0,"px":0.5,"py":0.5,"sx":1,"sy":1},"shape":"none","opacity":100,"blendMode":"normal","name":"This is an example o","description":"","links":[],"textSlots":{"body":{"text":"<p><em>This is an example of HTTP request in plain text. This is what a server sees once it decrypts a request</em></p>","halign":"left","valign":"top","paddingLeft":0,"paddingRight":0,"paddingTop":0,"paddingBottom":0,"color":"rgba(0,0,0,1.0)","fontSize":14,"whiteSpace":"normal","font":"Arial"}},"behavior":{"events":[]},"selfOpacity":100,"visible":true,"tags":[],"clip":false,"effects":[],"interactionMode":"tooltip","shapeProps":{},"tooltipBackground":"rgba(230,230,230,1.0)","tooltipColor":"rgba(30,30,30,1.0)","id":"vxEO3Rp4T"}]},{"shapeProps":{"cornerRadius":0,"fill":{"type":"solid","color":"rgba(240,240,240,1.0)"},"strokeColor":"rgba(30,30,30,1.0)","strokeSize":0,"strokePattern":"solid"},"shape":"rect","cursor":"default","area":{"x":60,"y":460,"w":140,"h":40,"r":0,"px":0.5,"py":0.5,"sx":1,"sy":1},"opacity":100,"blendMode":"normal","name":"format-part-template","description":"","links":[],"textSlots":{"body":{"text":"<p>format-part-template</p>","color":"rgba(0,0,0,1.0)","halign":"center","valign":"middle","fontSize":14,"whiteSpace":"normal","font":"Arial","paddingLeft":0,"paddingRight":0,"paddingTop":0,"paddingBottom":0}},"behavior":{"events":[{"id":"qJNWGyj27","event":"init","actions":[{"id":"elGF956TO","element":"self","method":"copyEvents","args":{"destination":"tag: format-part"}}]},{"id":"OVgooSugH","event":"mousein","actions":[{"id":"Sq-76N4ik","element":"self","method":"set","args":{"field":"shapeProps.fill","value":{"type":"solid","color":"rgba(160, 192, 193, 0.32)"},"animated":true,"animationDuration":0.2,"transition":"ease-in-out","inBackground":false}}]},{"id":"OVgooSugH","event":"mouseout","actions":[{"id":"Sq-76N4ik","element":"self","method":"set","args":{"field":"shapeProps.fill","value":{"type":"solid","color":"rgba(240, 240, 240, 0)"},"animated":true,"animationDuration":0.2,"transition":"ease-in-out","inBackground":false}}]}]},"selfOpacity":100,"visible":true,"tags":["reset"],"clip":false,"effects":[],"interactionMode":"tooltip","tooltipBackground":"rgba(230,230,230,1.0)","tooltipColor":"rgba(30,30,30,1.0)","id":"KnLCSCUP_"},{"id":"7dU2eXDPs","shapeProps":{"cornerRadius":15,"fill":{"type":"solid","color":"rgba(240,240,240,1.0)"},"strokeColor":"rgba(182, 181, 181, 1)","strokeSize":1,"strokePattern":"solid"},"shape":"rect","cursor":"default","area":{"x":840,"y":20,"w":760,"h":420,"r":0,"px":0.5,"py":0.5,"sx":1,"sy":1},"opacity":100,"blendMode":"normal","name":"HTTP Response","description":"","links":[],"textSlots":{"body":{"text":"","color":"rgba(0,0,0,1.0)","halign":"center","valign":"middle","fontSize":14,"whiteSpace":"normal","font":"Arial","paddingLeft":0,"paddingRight":0,"paddingTop":0,"paddingBottom":0}},"behavior":{"events":[]},"selfOpacity":100,"visible":true,"tags":["reset"],"clip":false,"effects":[{"id":"EdOSUGWf2","effect":"drop-shadow","name":"Drop Shadow","args":{"color":"rgba(0,0,0,1.0)","dx":5,"dy":5,"blur":14,"opacity":50,"inside":false}}],"interactionMode":"tooltip","tooltipBackground":"rgba(230,230,230,1.0)","tooltipColor":"rgba(30,30,30,1.0)","childItems":[{"id":"ZzcE4-MmJV","shapeProps":{"cornerRadius":8.3,"fill":{"type":"solid","color":"rgba(255, 255, 255, 1)"},"strokeColor":"rgba(211, 211, 211, 1)","strokeSize":1,"strokePattern":"solid"},"shape":"rect","cursor":"default","area":{"x":20,"y":80,"w":720,"h":260,"r":0,"px":0.5,"py":0.5,"sx":1,"sy":1},"opacity":100,"blendMode":"normal","name":"Rect 13","description":"","links":[],"textSlots":{"body":{"text":"","color":"rgba(0,0,0,1.0)","halign":"center","valign":"middle","fontSize":14,"whiteSpace":"normal","font":"Arial","paddingLeft":0,"paddingRight":0,"paddingTop":0,"paddingBottom":0}},"behavior":{"events":[]},"selfOpacity":100,"visible":true,"tags":[],"clip":false,"effects":[],"interactionMode":"tooltip","tooltipBackground":"rgba(230,230,230,1.0)","tooltipColor":"rgba(30,30,30,1.0)","childItems":[{"id":"CKchbPlF7i","shapeProps":{"cornerRadius":0,"fill":{"type":"solid","color":"rgba(240, 240, 240, 0)"},"strokeColor":"rgba(30,30,30,1.0)","strokeSize":0,"strokePattern":"solid"},"shape":"rect","cursor":"pointer","area":{"x":20,"y":80,"w":140,"h":20,"r":0,"px":0.5,"py":0.5,"sx":1,"sy":1},"opacity":100,"blendMode":"normal","name":"Content-Length","description":"<p>The <strong>Content-Length</strong> header indicates the size of the message body, in bytes, sent to the recipient.</p>","links":[],"textSlots":{"body":{"text":"<p>Content-Length: 2399</p>","color":"rgba(0,0,0,1.0)","halign":"left","valign":"middle","fontSize":14,"whiteSpace":"normal","font":"Arial","paddingLeft":2,"paddingRight":2,"paddingTop":2,"paddingBottom":0}},"behavior":{"events":[]},"selfOpacity":100,"visible":true,"tags":["format-part"],"clip":false,"effects":[],"interactionMode":"tooltip","tooltipBackground":"rgba(230,230,230,1.0)","tooltipColor":"rgba(30,30,30,1.0)"},{"id":"AEilWthu7v","shapeProps":{"cornerRadius":0,"fill":{"type":"solid","color":"rgba(240, 240, 240, 0)"},"strokeColor":"rgba(30,30,30,1.0)","strokeSize":0,"strokePattern":"solid"},"shape":"rect","cursor":"pointer","area":{"x":95,"y":20,"w":30,"h":20,"r":0,"px":0.5,"py":0.5,"sx":1,"sy":1},"opacity":100,"blendMode":"normal","name":"HTTP status code","description":"<p>A <em>status code</em>, indicating success or failure of the request. Common status codes are 200, 404, or 302</p>","links":[],"textSlots":{"body":{"text":"<p>200</p>","color":"rgba(0,0,0,1.0)","halign":"left","valign":"middle","fontSize":14,"whiteSpace":"normal","font":"Arial","paddingLeft":2,"paddingRight":2,"paddingTop":2,"paddingBottom":0}},"behavior":{"events":[]},"selfOpacity":100,"visible":true,"tags":["format-part"],"clip":false,"effects":[],"interactionMode":"tooltip","tooltipBackground":"rgba(230,230,230,1.0)","tooltipColor":"rgba(30,30,30,1.0)"},{"id":"kA07l3KAvI","shapeProps":{"cornerRadius":0,"fill":{"type":"solid","color":"rgba(240, 240, 240, 0)"},"strokeColor":"rgba(30,30,30,1.0)","strokeSize":0,"strokePattern":"solid"},"shape":"rect","cursor":"pointer","area":{"x":135,"y":20,"w":25,"h":20,"r":0,"px":0.5,"py":0.5,"sx":1,"sy":1},"opacity":100,"blendMode":"normal","name":"HTTP Status text","description":"<p>A <em>status text</em>. A brief, purely informational, textual description of the status code to help a human understand the HTTP message.</p>","links":[],"textSlots":{"body":{"text":"<p>OK</p>","color":"rgba(0,0,0,1.0)","halign":"left","valign":"middle","fontSize":14,"whiteSpace":"normal","font":"Arial","paddingLeft":2,"paddingRight":2,"paddingTop":2,"paddingBottom":0}},"behavior":{"events":[]},"selfOpacity":100,"visible":true,"tags":["format-part"],"clip":false,"effects":[],"interactionMode":"tooltip","tooltipBackground":"rgba(230,230,230,1.0)","tooltipColor":"rgba(30,30,30,1.0)"},{"id":"6yeHTNyUip","shapeProps":{"cornerRadius":0,"fill":{"type":"solid","color":"rgba(240, 240, 240, 0)"},"strokeColor":"rgba(30,30,30,1.0)","strokeSize":0,"strokePattern":"solid"},"shape":"rect","cursor":"pointer","area":{"x":20,"y":20,"w":65,"h":20,"r":0,"px":0.5,"py":0.5,"sx":1,"sy":1},"opacity":100,"blendMode":"normal","name":"HTTP protocol version","description":"<p>HTTP protocol version</p>","links":[],"textSlots":{"body":{"text":"<p>HTTP/1.1</p>","color":"rgba(0,0,0,1.0)","halign":"left","valign":"middle","fontSize":14,"whiteSpace":"normal","font":"Arial","paddingLeft":2,"paddingRight":2,"paddingTop":2,"paddingBottom":0}},"behavior":{"events":[]},"selfOpacity":100,"visible":true,"tags":["format-part"],"clip":false,"effects":[],"interactionMode":"tooltip","tooltipBackground":"rgba(230,230,230,1.0)","tooltipColor":"rgba(30,30,30,1.0)"},{"id":"E4GjdiDUDW","shapeProps":{"cornerRadius":0,"fill":{"type":"solid","color":"rgba(240, 240, 240, 0)"},"strokeColor":"rgba(30,30,30,1.0)","strokeSize":0,"strokePattern":"solid"},"shape":"rect","cursor":"pointer","area":{"x":20,"y":40,"w":190,"h":20,"r":0,"px":0.5,"py":0.5,"sx":1,"sy":1},"opacity":100,"blendMode":"normal","name":"Server","description":"<p>The <strong>Server</strong> header describes the software used by the origin server that handled the request - that is, the server that generated the response</p>","links":[],"textSlots":{"body":{"text":"<p>Server: nginx/1.18.0 (Ubuntu)</p>","color":"rgba(0,0,0,1.0)","halign":"left","valign":"middle","fontSize":14,"whiteSpace":"normal","font":"Arial","paddingLeft":2,"paddingRight":2,"paddingTop":2,"paddingBottom":0}},"behavior":{"events":[]},"selfOpacity":100,"visible":true,"tags":["format-part"],"clip":false,"effects":[],"interactionMode":"tooltip","tooltipBackground":"rgba(230,230,230,1.0)","tooltipColor":"rgba(30,30,30,1.0)"},{"id":"nG5rNiR5XH","shapeProps":{"cornerRadius":0,"fill":{"type":"solid","color":"rgba(240, 240, 240, 0)"},"strokeColor":"rgba(30,30,30,1.0)","strokeSize":0,"strokePattern":"solid"},"shape":"rect","cursor":"pointer","area":{"x":20,"y":60,"w":155,"h":20,"r":0,"px":0.5,"py":0.5,"sx":1,"sy":1},"opacity":100,"blendMode":"normal","name":"Content-Type","description":"<p>The <strong>Content-Type</strong> representation header is used to indicate the original <a href=\"https://developer.mozilla.org/en-US/docs/Glossary/MIME_type\" rel=\"noopener noreferrer nofollow\"><u>media type</u></a> of the resource (prior to any content encoding applied for sending).</p>","links":[],"textSlots":{"body":{"text":"<p>Content-Type: text/html</p>","color":"rgba(0,0,0,1.0)","halign":"left","valign":"middle","fontSize":14,"whiteSpace":"normal","font":"Arial","paddingLeft":2,"paddingRight":2,"paddingTop":2,"paddingBottom":0}},"behavior":{"events":[]},"selfOpacity":100,"visible":true,"tags":["format-part"],"clip":false,"effects":[],"interactionMode":"tooltip","tooltipBackground":"rgba(230,230,230,1.0)","tooltipColor":"rgba(30,30,30,1.0)"},{"id":"upKpVs8jdO","shapeProps":{"cornerRadius":0,"fill":{"type":"solid","color":"rgba(240, 240, 240, 0)"},"strokeColor":"rgba(30,30,30,1.0)","strokeSize":0,"strokePattern":"solid"},"shape":"rect","cursor":"pointer","area":{"x":20,"y":100,"w":305,"h":20,"r":0,"px":0.5,"py":0.5,"sx":1,"sy":1},"opacity":100,"blendMode":"normal","name":"Last-Modified","description":"<p>The <strong>Last-Modified</strong> response HTTP header contains a date and time when the origin server believes the resource was last modified. It is used as a validator to determine if the resource is the same as the previously stored one. Less accurate than an <strong>ETag</strong> header, it is a fallback mechanism. Conditional requests containing <strong>If-Modified-Since</strong> or <strong>If-Unmodified-Since</strong> headers make use of this field.</p>","links":[],"textSlots":{"body":{"text":"<p>Last-Modified: Wed, 12 Oct 2022 18:29:20 GMT</p>","color":"rgba(0,0,0,1.0)","halign":"left","valign":"middle","fontSize":14,"whiteSpace":"normal","font":"Arial","paddingLeft":2,"paddingRight":2,"paddingTop":2,"paddingBottom":0}},"behavior":{"events":[]},"selfOpacity":100,"visible":true,"tags":["format-part"],"clip":false,"effects":[],"interactionMode":"tooltip","tooltipBackground":"rgba(230,230,230,1.0)","tooltipColor":"rgba(30,30,30,1.0)"},{"id":"fCF4929cez","shapeProps":{"cornerRadius":0,"fill":{"type":"solid","color":"rgba(240, 240, 240, 0)"},"strokeColor":"rgba(30,30,30,1.0)","strokeSize":0,"strokePattern":"solid"},"shape":"rect","cursor":"pointer","area":{"x":20,"y":140,"w":145,"h":20,"r":0,"px":0.5,"py":0.5,"sx":1,"sy":1},"opacity":100,"blendMode":"normal","name":"ETag","description":"<p>The <strong>ETag</strong> (or <strong>entity tag</strong>) HTTP response header is an identifier for a specific version of a resource. It lets caches be more efficient and save bandwidth, as a web server does not need to resend a full response if the content was not changed. Additionally, etags help to prevent simultaneous updates of a resource from overwriting each other (<a href=\"https://developer.mozilla.org/en-US/docs/Web/HTTP/Headers/ETag#avoiding_mid-air_collisions\" rel=\"noopener noreferrer nofollow\"><u>\"mid-air collisions\"</u></a>).</p>","links":[],"textSlots":{"body":{"text":"<p>ETag: \"63470780-95f\"</p>","color":"rgba(0,0,0,1.0)","halign":"left","valign":"middle","fontSize":14,"whiteSpace":"normal","font":"Arial","paddingLeft":2,"paddingRight":2,"paddingTop":2,"paddingBottom":0}},"behavior":{"events":[]},"selfOpacity":100,"visible":true,"tags":["format-part"],"clip":false,"effects":[],"interactionMode":"tooltip","tooltipBackground":"rgba(230,230,230,1.0)","tooltipColor":"rgba(30,30,30,1.0)"},{"id":"zmTkeNOjLL","shapeProps":{"cornerRadius":0,"fill":{"type":"solid","color":"rgba(240, 240, 240, 0)"},"strokeColor":"rgba(30,30,30,1.0)","strokeSize":0,"strokePattern":"solid"},"shape":"rect","cursor":"pointer","area":{"x":20,"y":120,"w":150,"h":20,"r":0,"px":0.5,"py":0.5,"sx":1,"sy":1},"opacity":100,"blendMode":"normal","name":"Connection","description":"<p>The <strong>Connection</strong> general header controls whether the network connection stays open after the current transaction finishes. If the value sent is <strong>keep-alive</strong>, the connection is persistent and not closed, allowing for subsequent requests to the same server to be done.</p>","links":[],"textSlots":{"body":{"text":"<p>Connection: keep-alive</p>","color":"rgba(0,0,0,1.0)","halign":"left","valign":"middle","fontSize":14,"whiteSpace":"normal","font":"Arial","paddingLeft":2,"paddingRight":2,"paddingTop":2,"paddingBottom":0}},"behavior":{"events":[]},"selfOpacity":100,"visible":true,"tags":["format-part"],"clip":false,"effects":[],"interactionMode":"tooltip","tooltipBackground":"rgba(230,230,230,1.0)","tooltipColor":"rgba(30,30,30,1.0)"},{"id":"0DvzEBKWQU","shapeProps":{"cornerRadius":0,"fill":{"type":"solid","color":"rgba(240, 240, 240, 0)"},"strokeColor":"rgba(30,30,30,1.0)","strokeSize":0,"strokePattern":"solid"},"shape":"rect","cursor":"pointer","area":{"x":20,"y":180,"w":680,"h":20,"r":0,"px":0.5,"py":0.5,"sx":1,"sy":1},"opacity":100,"blendMode":"normal","name":"blank line","description":"<p>A blank line indicating all meta-information for the response has been sent. Anything that goes after this line will be treated as a response body</p>","links":[],"textSlots":{"body":{"text":"<p><em> empty line</em></p>","color":"rgba(43, 168, 173, 1)","halign":"left","valign":"middle","fontSize":14,"whiteSpace":"normal","font":"Arial","paddingLeft":2,"paddingRight":2,"paddingTop":2,"paddingBottom":0}},"behavior":{"events":[]},"selfOpacity":100,"visible":true,"tags":["format-part"],"clip":false,"effects":[],"interactionMode":"tooltip","tooltipBackground":"rgba(230,230,230,1.0)","tooltipColor":"rgba(30,30,30,1.0)"},{"id":"qybBTOFMMp","shapeProps":{"cornerRadius":0,"fill":{"type":"solid","color":"rgba(240, 240, 240, 0)"},"strokeColor":"rgba(30,30,30,1.0)","strokeSize":0,"strokePattern":"solid"},"shape":"rect","cursor":"pointer","area":{"x":20,"y":200,"w":680,"h":40,"r":0,"px":0.5,"py":0.5,"sx":1,"sy":1},"opacity":100,"blendMode":"normal","name":"Response body","description":"<p>An optional <em>body</em> containing data associated with the request (like content of an HTML form), or the document associated with a response. The presence of the body and its size is specified by the start-line and HTTP headers.</p>","links":[],"textSlots":{"body":{"text":"<p><em>Data</em></p>","color":"rgba(43, 168, 173, 1)","halign":"left","valign":"middle","fontSize":14,"whiteSpace":"normal","font":"Arial","paddingLeft":2,"paddingRight":2,"paddingTop":2,"paddingBottom":0}},"behavior":{"events":[]},"selfOpacity":100,"visible":true,"tags":["format-part"],"clip":false,"effects":[],"interactionMode":"tooltip","tooltipBackground":"rgba(230,230,230,1.0)","tooltipColor":"rgba(30,30,30,1.0)"},{"id":"2whRAd3ca","shapeProps":{"cornerRadius":0,"fill":{"type":"solid","color":"rgba(240, 240, 240, 0)"},"strokeColor":"rgba(30,30,30,1.0)","strokeSize":0,"strokePattern":"solid"},"shape":"rect","cursor":"pointer","area":{"x":20,"y":160,"w":145,"h":20,"r":0,"px":0.5,"py":0.5,"sx":1,"sy":1},"opacity":100,"blendMode":"normal","name":"Accept-Ranges","description":"<p>The <strong>Accept-Ranges</strong> HTTP response header is a marker used by the server to advertise its support for partial requests from the client for file downloads. The value of this field indicates the unit that can be used to define a range.</p><p></p><p>In the presence of an <strong>Accept-Ranges</strong> header, the browser may try to <em>resume</em> an interrupted download instead of trying to restart the download.</p>","links":[],"textSlots":{"body":{"text":"<p>Accept-Ranges: bytes</p>","color":"rgba(0,0,0,1.0)","halign":"left","valign":"middle","fontSize":14,"whiteSpace":"normal","font":"Arial","paddingLeft":2,"paddingRight":2,"paddingTop":2,"paddingBottom":0}},"behavior":{"events":[]},"selfOpacity":100,"visible":true,"tags":["format-part"],"clip":false,"effects":[],"interactionMode":"tooltip","tooltipBackground":"rgba(230,230,230,1.0)","tooltipColor":"rgba(30,30,30,1.0)"}]},{"id":"FwItM4NXmP","cursor":"default","area":{"x":260,"y":17,"w":220,"h":23,"r":0,"px":0.5,"py":0.5,"sx":1,"sy":1},"shape":"none","opacity":100,"blendMode":"normal","name":"HTTP Request Format","description":"","links":[],"textSlots":{"body":{"text":"<p><strong>HTTP Response Format</strong></p>","halign":"left","valign":"top","paddingLeft":0,"paddingRight":0,"paddingTop":0,"paddingBottom":0,"color":"rgba(0,0,0,1.0)","fontSize":18,"whiteSpace":"normal","font":"Arial"}},"behavior":{"events":[]},"selfOpacity":100,"visible":true,"tags":[],"clip":false,"effects":[],"interactionMode":"tooltip","shapeProps":{},"tooltipBackground":"rgba(230,230,230,1.0)","tooltipColor":"rgba(30,30,30,1.0)"},{"id":"0NGncIfIRf","shapeProps":{"cornerRadius":9.1,"fill":{"type":"solid","color":"rgba(67, 179, 217, 1)"},"strokeColor":"rgba(30,30,30,1.0)","strokeSize":0,"strokePattern":"solid"},"shape":"rect","cursor":"pointer","area":{"x":130,"y":360,"w":240,"h":40,"r":0,"px":0.5,"py":0.5,"sx":1,"sy":1},"opacity":100,"blendMode":"normal","name":"Rounded Rect","description":"","links":[],"textSlots":{"body":{"text":"<p>Back to HTTP Request</p>","color":"rgba(255, 255, 255, 1)","halign":"center","valign":"middle","fontSize":14,"whiteSpace":"normal","font":"Arial","paddingLeft":0,"paddingRight":0,"paddingTop":0,"paddingBottom":0}},"behavior":{"events":[{"id":"bZ_dwVY97","event":"clicked","actions":[{"id":"7cYBvsIkD","element":"#ZepfYjDTA","method":"show","args":{"animated":false,"animationDuration":0.5,"transition":"ease-out","inBackground":false}},{"id":"xUjXL9xk4","element":"#7dU2eXDPs","method":"hide","args":{"animated":true,"animationDuration":0.5,"transition":"ease-out","inBackground":false}}]}]},"selfOpacity":100,"visible":true,"tags":["buttons"],"clip":false,"effects":[],"interactionMode":"tooltip","tooltipBackground":"rgba(230,230,230,1.0)","tooltipColor":"rgba(30,30,30,1.0)"},{"id":"ou3W3eFjSE","shapeProps":{"cornerRadius":9.1,"fill":{"type":"solid","color":"rgba(210, 208, 208, 1)"},"strokeColor":"rgba(0, 0, 0, 1)","strokeSize":0,"strokePattern":"solid"},"shape":"rect","cursor":"pointer","area":{"x":390,"y":360,"w":240,"h":40,"r":0,"px":0.5,"py":0.5,"sx":1,"sy":1},"opacity":100,"blendMode":"normal","name":"Rounded Rect 2","description":"","links":[],"textSlots":{"body":{"text":"<p>Close</p>","color":"rgba(0,0,0,1.0)","halign":"center","valign":"middle","fontSize":14,"whiteSpace":"normal","font":"Arial","paddingLeft":0,"paddingRight":0,"paddingTop":0,"paddingBottom":0}},"behavior":{"events":[{"id":"Yiewrv6za","event":"clicked","actions":[{"id":"XBpbsyKU4","element":"#7dU2eXDPs","method":"hide","args":{"animated":true,"animationDuration":0.5,"transition":"ease-out","inBackground":false}}]}]},"selfOpacity":100,"visible":true,"tags":["buttons"],"clip":false,"effects":[],"interactionMode":"tooltip","tooltipBackground":"rgba(230,230,230,1.0)","tooltipColor":"rgba(30,30,30,1.0)"}]},{"id":"M3wilEsEE","shapeProps":{"cornerRadius":9.1,"fill":{"type":"solid","color":"rgba(210, 208, 208, 1)"},"strokeColor":"rgba(0, 0, 0, 1)","strokeSize":0,"strokePattern":"solid"},"shape":"rect","cursor":"pointer","area":{"x":260,"y":460,"w":240,"h":40,"r":0,"px":0.5,"py":0.5,"sx":1,"sy":1},"opacity":100,"blendMode":"normal","name":"Rounded Rect 3","description":"","links":[],"textSlots":{"body":{"text":"<p>button template</p>","color":"rgba(0,0,0,1.0)","halign":"center","valign":"middle","fontSize":14,"whiteSpace":"normal","font":"Arial","paddingLeft":0,"paddingRight":0,"paddingTop":0,"paddingBottom":0}},"behavior":{"events":[{"id":"nKC4S7XVn","event":"mousein","actions":[{"id":"9t5G-r1Z7","element":"self","method":"set","args":{"field":"opacity","value":80,"animated":true,"animationDuration":0.2,"transition":"ease-in-out","inBackground":false}}]},{"id":"nKC4S7XVn","event":"mouseout","actions":[{"id":"9t5G-r1Z7","element":"self","method":"set","args":{"field":"opacity","value":100,"animated":true,"animationDuration":0.2,"transition":"ease-in-out","inBackground":false}}]},{"id":"Ml1vi532N","event":"init","actions":[{"id":"q5-9QUVqG","element":"self","method":"copyEvents","args":{"destination":"tag: buttons"}}]}]},"selfOpacity":100,"visible":true,"tags":["reset"],"clip":false,"effects":[],"interactionMode":"tooltip","tooltipBackground":"rgba(230,230,230,1.0)","tooltipColor":"rgba(30,30,30,1.0)"}]}],"interactionMode":"tooltip"}],"publicLink":"/docs/https-request"}